MANIFEST.in
README.rst
setup.py
django_graceful_session_cleanup.egg-info/PKG-INFO
django_graceful_session_cleanup.egg-info/SOURCES.txt
django_graceful_session_cleanup.egg-info/dependency_links.txt
django_graceful_session_cleanup.egg-info/not-zip-safe
django_graceful_session_cleanup.egg-info/requires.txt
django_graceful_session_cleanup.egg-info/top_level.txt
graceful_session_cleanup/__init__.py
graceful_session_cleanup/models.py
graceful_session_cleanup/management/__init__.py
graceful_session_cleanup/management/commands/__init__.py
graceful_session_cleanup/management/commands/graceful_session_cleanup.py