Metadata-Version: 1.0
Name: django-graceful-session-cleanup
Version: 0.2.2
Summary: A simple management command that can delete expired sessions from large session tables without killing the site.
Home-page: http://github.com/stefanfoulis/django-graceful-session-cleanup
Author: Stefan Foulis
Author-email: stefan@foulis.ch
License: BSD
Platform: OS Independent
Classifier: Development Status :: 4 - Beta
Classifier: Framework :: Django
Classifier: Intended Audience :: Developers
Classifier: License :: OSI Approved :: BSD License
Classifier: Operating System :: OS Independent
Classifier: Programming Language :: Python
Classifier: Topic :: Internet :: WWW/HTTP
